podex_pod/__init__.py
podex_pod-0.0.1.dist-info/METADATA
podex_pod-0.0.1.dist-info/WHEEL
podex_pod-0.0.1.dist-info/entry_points.txt
podex_pod-0.0.1.dist-info/RECORD
