Metadata-Version: 2.4
Name: podex-pod
Version: 0.0.1
Summary: Podex Local Pod - Self-hosted compute agent for Podex
Project-URL: Homepage, https://podex.dev
Project-URL: Documentation, https://docs.podex.dev/local-pods
Project-URL: Repository, https://github.com/podex/podex
Author-email: Podex <support@podex.dev>
License: MIT
Keywords: agent,ai,coding,compute,local-pod,podex
Classifier: Development Status :: 1 - Planning
Classifier: Environment :: Console
Classifier: Intended Audience :: Developers
Classifier: License :: OSI Approved :: MIT License
Classifier: Operating System :: OS Independent
Classifier: Programming Language :: Python :: 3
Classifier: Programming Language :: Python :: 3.11
Classifier: Programming Language :: Python :: 3.12
Classifier: Topic :: Software Development
Requires-Python: >=3.11
